AUTHORS
CHANGELOG.txt
DESCRIPTION
LICENSE
MANIFEST.in
setup.py
django_multilingual_orgs.egg-info/PKG-INFO
django_multilingual_orgs.egg-info/SOURCES.txt
django_multilingual_orgs.egg-info/dependency_links.txt
django_multilingual_orgs.egg-info/requires.txt
django_multilingual_orgs.egg-info/top_level.txt
multilingual_orgs/__init__.py
multilingual_orgs/admin.py
multilingual_orgs/cms_plugins.py
multilingual_orgs/models.py
multilingual_orgs/settings.py
multilingual_orgs/migrations/0001_initial.py
multilingual_orgs/migrations/0002_auto__add_organizationpersonrole.py
multilingual_orgs/migrations/0003_rename_translations.py
multilingual_orgs/migrations/0004_auto__add_organizationtranslation__add_unique_organizationtranslation_.py
multilingual_orgs/migrations/0005_move_from_simpletranslation_to_hvad.py
multilingual_orgs/migrations/0006_auto__del_organizationtranslationrenamed.py
multilingual_orgs/migrations/__init__.py
multilingual_orgs/templates/multilingual_orgs/organization_plugin.html
multilingual_orgs/tests/__init__.py
multilingual_orgs/tests/factories.py
multilingual_orgs/tests/models_tests.py
multilingual_orgs/tests/runtests.py
multilingual_orgs/tests/south_settings.py
multilingual_orgs/tests/test_settings.py
multilingual_orgs/tests/urls.py
multilingual_orgs/tests/test_app/__init__.py
multilingual_orgs/tests/test_app/models.py
multilingual_orgs/tests/test_app/templates/base.html
multilingual_orgs/tests/test_app/templates/standard.html