Metadata-Version: 1.0
Name: django-multilingual-orgs
Version: 1.0
Summary: An app for showing localized versions of organization profiles. E.g. as plugin
